atvp003.v
// Write your modules here!
module atvp003(A,P,W,M,S);
  input P,W,M,S;
  output A;
  assign A =(M) | (S & P) | (W & S);
endmodule

atvp003_tb.v
`timescale 1ns/1ns
`include "atvp003.v"

module atvp003_tb;

    reg P,W,M,S;
    wire A;
    atvp003 uut(A,P,W,M,S);

    initial begin
        $dumpfile("atvp003.vcd");
        $dumpvars(0, atvp003_tb);

        P = 0; W = 0; M = 0; S = 0; #30;
        P = 0; W = 0; M = 0; S = 1; #30;
        P = 0; W = 0; M = 1; S = 0; #30;
        P = 0; W = 0; M = 1; S = 1; #30;
        P = 0; W = 1; M = 0; S = 0; #30;
        P = 0; W = 1; M = 0; S = 1; #30;
        P = 0; W = 1; M = 1; S = 0; #30;
        P = 0; W = 1; M = 1; S = 1; #30;
        P = 1; W = 0; M = 0; S = 0; #30;
        P = 1; W = 0; M = 0; S = 1; #30;
        P = 1; W = 0; M = 1; S = 0; #30;
        P = 1; W = 0; M = 1; S = 1; #30;
        P = 1; W = 1; M = 0; S = 0; #30;
        P = 1; W = 1; M = 0; S = 1; #30;
        P = 1; W = 1; M = 1; S = 0; #30;
        P = 1; W = 1; M = 1; S = 1; #30;

        $display("Teste completo");
    end

endmodule

atvp003.vcd
$date
	Fri Sep 06 10:42:31 2024
$end
$version
	Icarus Verilog
$end
$timescale
	1ns
$end
$scope module atvp003_tb $end
$var wire 1 ! A $end
$var reg 1 " M $end
$var reg 1 # P $end
$var reg 1 $ S $end
$var reg 1 % W $end
$scope module uut $end
$var wire 1 ! A $end
$var wire 1 " M $end
$var wire 1 # P $end
$var wire 1 $ S $end
$var wire 1 % W $end
$upscope $end
$upscope $end
$enddefinitions $end
$comment Show the parameter values. $end
$dumpall
$end
#0
$dumpvars
0%
0$
0#
0"
0!
$end
#30
1$
#60
1!
0$
1"
#90
1$
#120
0!
0$
0"
1%
#150
1!
1$
#180
0$
1"
#210
1$
#240
0!
0$
0"
0%
1#
#270
1!
1$
#300
0$
1"
#330
1$
#360
0!
0$
0"
1%
#390
1!
1$
#420
0$
1"
#450
1$
